geneweaver/core/__init__.py
geneweaver/core/config.py
geneweaver/core/config_class.py
geneweaver/core/enum.py
geneweaver/core/exc.py
geneweaver/core/mapping.py
geneweaver/core/parse/__init__.py
geneweaver/core/parse/batch.py
geneweaver/core/parse/csv.py
geneweaver/core/parse/enum.py
geneweaver/core/parse/exceptions.py
geneweaver/core/parse/numpy.py
geneweaver/core/parse/score.py
geneweaver/core/parse/threshold.py
geneweaver/core/parse/utils.py
geneweaver/core/parse/xlsx.py
geneweaver/core/publication/__init__.py
geneweaver/core/publication/pubmed.py
geneweaver/core/render/__init__.py
geneweaver/core/render/batch.py
geneweaver/core/render/csv.py
geneweaver/core/render/gene_list.py
geneweaver/core/schema/__init__.py
geneweaver/core/schema/api_response.py
geneweaver/core/schema/batch.py
geneweaver/core/schema/gene.py
geneweaver/core/schema/geneset.py
geneweaver/core/schema/group.py
geneweaver/core/schema/legacy_api.py
geneweaver/core/schema/messages.py
geneweaver/core/schema/ontology.py
geneweaver/core/schema/project.py
geneweaver/core/schema/publication.py
geneweaver/core/schema/score.py
geneweaver/core/schema/species.py
geneweaver/core/schema/stubgenerator.py
geneweaver/core/schema/user.py
geneweaver/core/threshold.py
geneweaver/core/types.py
geneweaver/core/utils.py
geneweaver_core-0.9.1.dist-info/LICENSE
geneweaver_core-0.9.1.dist-info/METADATA
geneweaver_core-0.9.1.dist-info/WHEEL
geneweaver_core-0.9.1.dist-info/RECORD
