Metadata-Version: 2.1
Name: geneweaver-core
Version: 0.9.1
Summary: The core of the Jax-Geneweaver Python library
Home-page: https://thejacksonlaboratory.github.io/geneweaver-docs/
License: Apache-2.0
Author: Jax Computational Sciences
Author-email: cssc@jax.org
Requires-Python: >=3.9,<4.0
Classifier: License :: OSI Approved :: Apache Software License
Classifier: Programming Language :: Python :: 3
Classifier: Programming Language :: Python :: 3.9
Classifier: Programming Language :: Python :: 3.10
Classifier: Programming Language :: Python :: 3.11
Classifier: Programming Language :: Python :: 3.12
Requires-Dist: numpy (>=1.22,<2)
Requires-Dist: openpyxl (>=3.1.2,<4.0.0)
Requires-Dist: pandas (>=1.5,<3)
Requires-Dist: pydantic[dotenv] (>=1.10,<2.0)
Requires-Dist: requests (>=2.31.0,<3.0.0)
Project-URL: Repository, https://github.com/TheJacksonLaboratory/geneweaver-client
